[
  {
    "question": "소방시설법상 '종합점검'의 대상이 아닌 건축물은?",
    "options": ["연면적 5,000㎡ 이상이고 스프링클러가 설치된 특정소방대상물", "물분무등소화설비가 설치된 연면적 3,000㎡ 이상인 건물", "층수가 11층 이상인 모든 건물", "단층 창고 (스프링클러 없음)"],
    "answer": 3,
    "explanation": "기본적으로 스프링클러나 물분무등이 있거나 규모가 큰 건물이 대상이며, **단순 창고**는 제외될 수 있습니다.",
    "difficulty": 1
  },
  {
    "question": "소방시설관리업의 보조 기술인력 1명이 하루에 추가로 점검할 수 있는 면적은?",
    "options": ["500㎡", "1,000㎡", "2,000㎡", "3,000㎡"],
    "answer": 2,
    "explanation": "보조 인력이 추가될 때마다 하루 점검 한도 면적이 **2,000㎡**씩 늘어납니다.",
    "difficulty": 2
  },
  {
    "question": "소방본부장 또는 소방서장이 화재안전조사 결과를 관계인에게 통보할 때의 기간은?",
    "options": ["즉시", "7일 이내", "14일 이내", "30일 이내"],
    "answer": 1,
    "explanation": "조사 완료 후 **7일 이내**에 서면으로 결과를 알려야 합니다.",
    "difficulty": 2
  },
  {
    "question": "소화기구의 화재안전기준에서 '대형소화기'의 충전량 기준 중 ABC분말의 양은?",
    "options": ["10kg 이상", "20kg 이상", "30kg 이상", "50kg 이상"],
    "answer": 1,
    "explanation": "ABC 분말 소화기는 **20kg 이상**이어야 대형으로 분류됩니다.",
    "difficulty": 1
  },
  {
    "question": "스프링클러 설비의 점검 중 '교차배관'의 관경은 최소 몇 mm 이상인가?",
    "options": ["25mm", "32mm", "40mm", "50mm"],
    "answer": 2,
    "explanation": "유량 확보를 위해 교차배관은 최소 **40mm 이상**이어야 합니다.",
    "difficulty": 3
  },
  {
    "question": "소방시설관리사 자격증을 분실하여 재발급받은 후, 구 자격증을 찾았다면 어떻게 해야 하는가?",
    "options": ["그냥 보관한다", "즉시 폐기한다", "10일 이내에 소방청장에게 반납한다", "친구에게 준다"],
    "answer": 2,
    "explanation": "이중 소지를 막기 위해 발견 즉시 **반납**해야 합니다.",
    "difficulty": 1
  },
  {
    "question": "피난시설의 폐쇄 행위에 대한 과태료 부과 시, '폐쇄'에 해당하지 않는 것은?",
    "options": ["출입문을 도어체크로 고정하여 열어둔 상태", "출입문을 잠금장치로 잠근 상태", "출입문 앞에 물건을 쌓아둔 상태", "출입문 제거"],
    "answer": 0,
    "explanation": "열어둔 것은 폐쇄가 아니지만, **잠그거나 물건을 쌓는 것**은 명백한 위반입니다.",
    "difficulty": 2
  },
  {
    "question": "소방시설관리업의 행정처분 중 '영업정지 6개월'을 받은 업체가 계속 영업을 하면?",
    "options": ["경고", "영업정지 1년", "등록 취소", "과태료 증액"],
    "answer": 2,
    "explanation": "정지 기간 중 업무 수행은 가장 무거운 처분인 **등록 취소** 사유입니다.",
    "difficulty": 1
  },
  {
    "question": "옥내소화전 설비의 수조 설치 기준 중 '동결 방지 조치'를 하지 않아도 되는 경우는?",
    "options": ["항상 영하인 곳", "동결의 우려가 없는 장소에 설치한 경우", "건물 옥상", "상관없음"],
    "answer": 1,
    "explanation": "실내 등 **얼 가능성이 없는** 곳이라면 별도의 보온 조치가 필요 없습니다.",
    "difficulty": 1
  },
  {
    "question": "자체점검 이행계획서의 완료 예정 기한은 점검 종료일부터 최대 며칠 이내로 정하는가?",
    "options": ["10일", "15일", "20일", "30일"],
    "answer": 2,
    "explanation": "보통 **20일** 이내에 수리를 완료하겠다는 계획을 세워 제출합니다.",
    "difficulty": 3
  },
  {
    "question": "소방시설관리사의 직무 중 '점검표의 작성'은 누구의 책임하에 이루어지는가?",
    "options": ["보조 인력", "건물 주인", "현장 점검을 수행한 소방시설관리사", "행정 직원"],
    "answer": 2,
    "explanation": "기술적 판단이 들어가는 점검표는 **관리사**가 직접 책임지고 작성해야 합니다.",
    "difficulty": 1
  },
  {
    "question": "스프링클러 설비 중 '감압밸브'의 설치 목적은?",
    "options": ["수압을 높이기 위해", "하층부 헤드의 규정 방수압력을 초과하는 구역의 압력을 조절하기 위해", "물 농도 조절", "상관없음"],
    "answer": 1,
    "explanation": "건물이 높을 때 아래층은 압력이 너무 세서 헤드가 망가질 수 있으므로 **압력을 낮춰주는** 밸브입니다.",
    "difficulty": 2
  },
  {
    "question": "소방시설관리업 등록 신청 시 제출하는 '기술인력 보유 현황' 서류에 포함되는 것은?",
    "options": ["기술인력의 주민등록초본", "기술인력 자격증 수첩 사본 및 건강보험 자격득실확인서", "가족관계증명서", "상관없음"],
    "answer": 1,
    "explanation": "실제로 해당 업체에 **상근**하고 있는지 확인하기 위해 보험 서류와 자격증을 제출합니다.",
    "difficulty": 2
  },
  {
    "question": "이산화탄소 소화설비의 점검 시 '중량 측정'을 하는 이유는?",
    "options": ["무게를 달아보려고", "약제 용기 내 가스의 누설 여부를 확인하기 위해", "용기 디자인 확인", "상관없음"],
    "answer": 1,
    "explanation": "가스가 샜는지는 눈으로 안 보이므로 **무게**를 재서 줄어들었는지 체크합니다.",
    "difficulty": 1
  },
  {
    "question": "피난층 이외의 층에서 피난구 유도등의 설치 위치는?",
    "options": ["바닥", "거실에서 복도로 나가는 출입구 상단", "창문 옆", "화장실 내부"],
    "answer": 1,
    "explanation": "탈출로인 **출입구 위쪽**에 달아 멀리서도 보이게 합니다.",
    "difficulty": 1
  },
  {
    "question": "소방시설관리사 자격 정지 처분을 받은 자가 그 기간에 점검 업무를 수행한 경우?",
    "options": ["자격 취소", "주의", "정지 기간 연장", "벌금 10만원"],
    "answer": 0,
    "explanation": "법을 어기고 무면허로 업무를 본 것이므로 **자격이 취소**됩니다.",
    "difficulty": 2
  },
  {
    "question": "연결송수관설비의 방수구가 11층 이상인 경우 '쌍구형'을 쓰는 이유가 아닌 것은?",
    "options": ["많은 유량이 필요해서", "호스 두 개를 동시에 연결하려고", "모양이 예뻐서", "화재 진압의 효율성을 위해"],
    "answer": 2,
    "explanation": "**디자인**은 법적 강제 사유가 아닙니다.",
    "difficulty": 1
  },
  {
    "question": "자체점검 결과 보고서에 첨부하는 '소방시설등 점검표'의 보존 기간은?",
    "options": ["1년", "2년", "5년", "영구"],
    "answer": 1,
    "explanation": "관계인은 모든 점검 관련 기록을 **2년간** 보관해야 합니다.",
    "difficulty": 1
  },
  {
    "question": "소방시설관리업자가 점검을 수탁했을 때, 점검 인력을 배치하는 기준일은?",
    "options": ["계약일", "실제 점검을 실시한 날", "돈을 받은 날", "보고서 제출일"],
    "answer": 1,
    "explanation": "**실제 현장에 나간 날**을 기준으로 인력 배치 기준을 적용합니다.",
    "difficulty": 2
  },
  {
    "question": "스프링클러 설비의 '송수구' 설치 위치 기준은?",
    "options": ["건물 내부", "소방차가 쉽게 접근할 수 있는 노출된 장소", "옥상", "지하 주차장"],
    "answer": 1,
    "explanation": "소방차에서 물을 공급받아야 하므로 **밖에서 잘 보이는** 곳에 둡니다.",
    "difficulty": 1
  },
  {
    "question": "소방시설관리사 시험에서 면제받을 수 있는 과목은 주로 어떤 경력자에게 주어지는가?",
    "options": ["운전경력자", "소방공무원 15년 이상 또는 소방기술사 자격자 등", "일반 회사원", "대학생"],
    "answer": 1,
    "explanation": "전문성이 인정되는 **고숙련자**에게 일부 과목 면제 혜택을 줍니다.",
    "difficulty": 3
  },
  {
    "question": "방염성능검사 결과 합격한 물품에 부착하는 것은?",
    "options": ["합격통지서", "방염성능검사 합격표시 (라벨 등)", "영수증", "주의사항"],
    "answer": 1,
    "explanation": "검사를 통과했음을 알리는 **합격 라벨**을 물품에 직접 붙입니다.",
    "difficulty": 1
  },
  {
    "question": "소방시설관리업자가 연간 점검 실적을 보고하지 않은 경우의 과태료는?",
    "options": ["100만원", "200만원", "300만원", "500만원"],
    "answer": 1,
    "explanation": "행정 보고 의무 위반으로 **200만원 이하**의 과태료가 부과될 수 있습니다.",
    "difficulty": 2
  },
  {
    "question": "옥내소화전 설비의 '방수압력' 측정 시 사용하는 도구는?",
    "options": ["줄자", "피토게이지 (Pitot Gauge)", "온도계", "저울"],
    "answer": 1,
    "explanation": "노즐에서 나오는 물의 힘을 측정하는 **피토게이지**를 씁니다.",
    "difficulty": 2
  },
  {
    "question": "자체점검 시 소방펌프의 '기동점'과 '정지점'을 설정하는 장치는?",
    "options": ["배터리", "압력챔버의 압력스위치", "벨트", "핸들"],
    "answer": 1,
    "explanation": "**압력스위치**의 눈금을 조절하여 언제 펌프가 돌고 멈출지 정합니다.",
    "difficulty": 2
  },
  {
    "question": "소방시설관리사의 자격취소 사유 중 '자격증 대여'에 대한 처벌은?",
    "options": ["1차 경고", "1차 자격취소", "벌금 5만원", "상관없음"],
    "answer": 1,
    "explanation": "자격증을 빌려주는 것은 매우 엄격하게 다스려 **즉시 취소**됩니다.",
    "difficulty": 1
  },
  {
    "question": "연결송수관설비의 배관 중 '습식'으로 설치해야 하는 건물의 높이 기준은?",
    "options": ["11층 이상", "31m 이상", "70m 이상", "상관없음"],
    "answer": 1,
    "explanation": "높이가 **31m**를 넘으면 빠른 방수를 위해 배관에 물이 차 있는 습식이어야 합니다.",
    "difficulty": 3
  },
  {
    "question": "자체점검 결과 보고를 받은 소방서장이 이행계획서의 내용이 미비하다고 판단하면?",
    "options": ["직접 고쳐준다", "보완 명령을 내린다", "무시한다", "상관없음"],
    "answer": 1,
    "explanation": "부실한 수리 계획에 대해서는 다시 제대로 계획을 세우라고 **보완 명령**을 합니다.",
    "difficulty": 1
  },
  {
    "question": "소방시설관리업의 기술인력 산정 시 '보조 인력'으로 인정되는 자격증은?",
    "options": ["소방설비기사, 산업기사, 소방안전관리자 등", "한자검정시험", "정보기기운용기능사", "상관없음"],
    "answer": 0,
    "explanation": "**소방 관련 자격**이 있어야 보조 인력으로 일할 수 있습니다.",
    "difficulty": 1
  },
  {
    "question": "스프링클러 배관의 '지지간격' 중 관경 50mm인 경우 최대 몇 m 이내인가?",
    "options": ["2.0m", "3.5m", "4.5m", "6.0m"],
    "answer": 2,
    "explanation": "배관이 처지지 않도록 **4.5m**마다 지지대를 설치해야 합니다.",
    "difficulty": 3
  },
  {
    "question": "소방시설관리업자가 사무실 주소를 변경했을 때 신고 기한은?",
    "options": ["7일 이내", "15일 이내", "30일 이내", "60일 이내"],
    "answer": 2,
    "explanation": "상호, 대표자, 소재지 변경은 **30일 이내**에 신고해야 합니다.",
    "difficulty": 2
  },
  {
    "question": "옥내소화전 노즐의 '방수구경' 표준은?",
    "options": ["10mm", "13mm", "19mm", "25mm"],
    "answer": 1,
    "explanation": "가장 많이 쓰이는 노즐 끝 구경은 **13mm**입니다.",
    "difficulty": 2
  },
  {
    "question": "자체점검(작동점검) 결과 보고서를 관할 소방서에 제출하는 주체는?",
    "options": ["관리업체", "건물 관계인(소유자, 관리자 등)", "소방공무원", "상관없음"],
    "answer": 1,
    "explanation": "점검은 업체가 대행하지만, 보고의 법적 의무는 **건물주(관계인)**에게 있습니다.",
    "difficulty": 1
  },
  {
    "question": "소방시설관리업의 등록권자는?",
    "options": ["소방청장", "시·도지사", "경찰청장", "시장"],
    "answer": 1,
    "explanation": "소방시설업 면허는 관할 **시·도지사**가 발급합니다.",
    "difficulty": 1
  },
  {
    "question": "점검 중 소방펌프의 '그랜드 패킹' 부위에서 물이 조금씩 떨어지는 것은 정상인가?",
    "options": ["정상 (윤활 및 냉각을 위해 필요)", "비정상 (즉시 수리)", "펌프 고장", "상관없음"],
    "answer": 0,
    "explanation": "패킹의 마찰열을 식히기 위해 **분당 수십 방울** 정도 떨어지는 것이 정상적인 관리 상태입니다.",
    "difficulty": 3
  },
  {
    "question": "소방시설관리사 자격증 재발급 시 수수료를 내는가?",
    "options": ["무료", "해당 시·도의 조례로 정하는 수수료 납부", "만원", "상관없음"],
    "answer": 1,
    "explanation": "행정 서비스 비용으로 일정 금액의 **수수료**를 내야 합니다.",
    "difficulty": 2
  },
  {
    "question": "화재안전조사를 거부·방해 또는 기피한 자에 대한 처벌은?",
    "options": ["300만원 이하의 벌금", "과태료 10만원", "훈방", "벌금 5,000만원"],
    "answer": 0,
    "explanation": "정당한 공무 집행을 방해한 것이므로 **벌금형**에 처해집니다.",
    "difficulty": 2
  },
  {
    "question": "스프링클러 설비의 '테스트 밸브' 설치 목적은?",
    "options": ["배관 청소", "실제 헤드가 터졌을 때와 같은 조건으로 펌프 기동 및 경보 작동 확인", "수조 물 빼기", "상관없음"],
    "answer": 1,
    "explanation": "실제로 불난 것처럼 물을 빼서 **시스템 전체가 잘 도는지** 시험하는 밸브입니다.",
    "difficulty": 1
  },
  {
    "question": "소방시설관리업자가 점검 인력을 배치할 때, '보조 인력'은 최대 몇 명까지 인정되는가?",
    "options": ["2명", "4명", "제한 없음", "상관없음"],
    "answer": 1,
    "explanation": "관리사 1명당 **보조 인력은 최대 4명**까지만 한 팀으로 인정됩니다.",
    "difficulty": 3
  },
  {
    "question": "점검 보고서의 '종합 의견'란에 반드시 포함되어야 하는 내용은?",
    "options": ["건물 가격", "점검 결과 발견된 불량 사항의 요약 및 조치 필요성", "대표자의 취미", "상관없음"],
    "answer": 1,
    "explanation": "가장 중요한 **결함 내용과 수리 방향**을 한눈에 알 수 있게 적어야 합니다.",
    "difficulty": 1
  },
  {
    "question": "소방시설관리사가 점검 후 '이중 취업' 사실이 적발되면?",
    "options": ["자격 취소", "주의", "월급 인상", "상관없음"],
    "answer": 0,
    "explanation": "상근 의무를 위반하고 두 곳 이상 적을 두는 것은 **자격 취소** 사유입니다.",
    "difficulty": 1
  },
  {
    "question": "옥내소화전 함 상부에 설치된 '적색 표시등'의 역할은?",
    "options": ["장식", "소화전 함의 위치를 멀리서도 알 수 있게 함", "불이 났음을 알림", "상관없음"],
    "answer": 1,
    "explanation": "어두운 복도에서도 **소화전의 위치**를 빨리 찾을 수 있게 해주는 표시등입니다.",
    "difficulty": 1
  },
  {
    "question": "자체점검 업무를 수행하는 관리업체의 '영업 범위'는?",
    "options": ["관할 시·도 내에서만 가능", "전국 어디서나 가능", "해당 동네만 가능", "상관없음"],
    "answer": 1,
    "explanation": "한 곳에 등록하면 **전국**의 소방 대상물을 점검할 수 있습니다.",
    "difficulty": 2
  },
  {
    "question": "스프링클러 배관 중 '교차배관'에서 '가지배관'으로 갈라지는 부분에 설치하는 것은?",
    "options": ["T자 연결 (티)", "엘보", "밸브", "상관없음"],
    "answer": 0,
    "explanation": "**티(T)** 배관을 사용하여 물을 분배합니다.",
    "difficulty": 1
  },
  {
    "question": "소방시설관리업자가 점검을 완료한 후 관계인에게 설명해야 할 의무가 있는가?",
    "options": ["예 (점검 결과 및 불량 사항에 대한 상세 설명)", "아니오 (보고서만 주면 됨)", "선택 사항", "상관없음"],
    "answer": 0,
    "explanation": "전문가로서 건물 주인에게 **위험 요소를 충분히 설명**할 의무가 있습니다.",
    "difficulty": 1
  },
  {
    "question": "점검 중 소방펌프의 '압력계'가 떨린다면 의심해야 할 원인은?",
    "options": ["펌프 회전 방향 반대", "공기 유입 또는 공동현상", "정상", "상관없음"],
    "answer": 1,
    "explanation": "배관 안에 **공기**가 찼거나 물 공급이 원활하지 않을 때 바늘이 떨릴 수 있습니다.",
    "difficulty": 3
  },
  {
    "question": "소방시설관리사의 자격시험은 몇 년마다 시행하는가?",
    "options": ["매년 1회 이상", "2년마다", "5년마다", "수시"],
    "answer": 0,
    "explanation": "수요 공급을 조절하기 위해 보통 **매년 1회** 정기적으로 시행합니다.",
    "difficulty": 1
  },
  {
    "question": "자체점검 시 사용하는 '방수압력 측정구'의 노즐 끝과 측정 도구 사이의 거리는?",
    "options": ["바짝 붙임", "노즐 구경의 1/2 지점 (약 D/2 거리)", "1m 뗌", "상관없음"],
    "answer": 1,
    "explanation": "가장 정확한 압력을 재기 위해 **노즐 구경의 절반** 정도 거리에서 측정합니다.",
    "difficulty": 3
  },
  {
    "question": "소방시설관리업 등록 시 필요한 기술인력 중 '주된 인력'은 몇 명인가?",
    "options": ["1명 이상", "2명 이상", "3명 이상", "5명 이상"],
    "answer": 0,
    "explanation": "최소 **소방시설관리사 1명**이 있어야 업체 등록이 가능합니다.",
    "difficulty": 1
  },
  {
    "question": "점검 보고서를 거짓으로 제출한 관계인에 대한 처벌은?",
    "options": ["벌금 10만원", "과태료 500만원 이하", "훈방", "벌금 1억"],
    "answer": 1,
    "explanation": "안전 정보를 속인 행위에 대해 무거운 **과태료**가 부과됩니다.",
    "difficulty": 2
  }
]
